{
  "basics": {
    "name": "Mahie Crabbe",
    "label": "Student",
    "picture": "https://mahi3crab.github.io/images/Screen Shot 2022-01-18 at 12.05.52 PM.png",
    "email": "mahi3@hawaii.edu",
    "phone": "808-386-4263",
    "website": "https://mahi3crab.github.io",
    "summary": "I am studying for a B.S. in Computer Science in the Department of Information and Computer Sciences at the University of Hawaii. I expect to graduate in Spring, 2024.",
    "location": {
      "address": "",
      "postalCode": "",
      "city": "Honolulu",
      "countryCode": "USA",
      "region": "Hawaii"
    },
    "profiles": [
      {
        "network": "github",
        "username": "mahi3crab",
        "url": "http://github.com/mahi3crab"
      },
      {
        "network": "linkedin",
        "username": "Mahie Crabbe",
        "url": "http://linkedin.com/in/mahie-crabbe"
      },
    ]
  },
  "interests": [
    {
      "name": "Software Engineering",
      "keywords": [
      ]
    },
    {
      "name": "Artificial Intelligence",
      "keywords": [
      ]
    },
    {
      "name": "Data Science",
      "keywords": [
      ]
    },
    {
      "name": "Hula",
      "keywords": [
      ]
    },
    {
      "name": "Water Sports",
      "keywords": [
      ]
    }
  ],
  "skills": [
    {
      "name": "Languages and Frameworks",
      "level": "",
      "keywords": [
        "Java",
        "JavaScript",
        "HTML",
        "CSS"
      ]
    },
    {
      "name": "Toolsets/OS",
      "level": "",
      "keywords": [
        "MacOS",
        "Git/GitHub",
        "Eclipse"
      ]
    }
  ],
  "education": [
    {
      "institution": "University of Hawaii, Honolulu, HI",
      "area": "Computer Science (expected Spring, 2024)",
      "studyType": "B.S.",
      "startDate": "2020-08-24",
      "endDate": "Present",
      "gpa": "3.65",
      "courses": [
        "ICS 314: Software Engineering I",
        "ICS 311: Algorithms",
        "ICS 212: C/C++ Programming",
        "ICS 241: Discrete Math II for CS",
        "ICS 211: Data Structures",
        "ICS 141: Discrete Math I for CS",
        "ICS 111: Intro to Java"
      ]
    }
  ],
  "work": [
    {
      "company": "Diamond Head Health Bar",
      "position": "Barista & Cashier",
      "website": "",
      "startDate": "2020-06-05",
      "endDate": "Present",
      "summary": "Working in the front of house as a cashier and working in the back of house as a barista making smoothies, juices, and acai bowls",
      "highlights": [
        "Fulfill hygenic practices when handelling food items",
        "Keeping track of inventory",
        "Customer Service",
      ]
    },
  ],
  "volunteer": [
    {
      "organization": "Shinnyo-En",
      "website": "",
      "position": "Member",
      "startDate": "2002-07-18",
      "endDate": "Present",
      "summary": "As a member I actively help with temple services, participate in neighborhood clean-ups, and volunteer in several positions at the Lantern FLoating Hawaii",
      "highlights": [
        "Helps guests at Lantern Floating Hawaii",
        "Help educate and integrate Hawaiian culture and perspective",
      ] 
    },
    {
      "organization": "PANDA",
      "website": "",
      "position": "Member",
      "startDate": "2020-09-01",
      "endDate": "Present",
      "summary": "As a member I attend weekly PANDA meetings and collaborate with fellow classmates to solve mock interview problems",
      "highlights": [
        "Practice coding & algorithm skills / knowledge",
        "Peer collaboration",
        "Mock interview question practice",
        "Assisting lower classmen"
      ] 
    },
  ],
  "awards": [
    {
      "title": "Manoa Academic Merit Scholarship",
      "date": "2020-Present",
      "awarder": "University of Hawaii at Manoa",
      "summary": "Scholarship is an automatic $2,000 scholarship per year for four years of undergraduate study for first-time degree seeking students. Students must have a 3.5 GPA, 1200 SAT or 23 ACT upon the time of application to UH Manoa."
    },
    {
      "title": "UMH Second Century Scholarship",
      "date": "2020-Present",
      "awarder": "University of Hawaii at Manoa",
      "summary": "The scholarship is available to Native Hawaiian students with demonstrated financial need pursuing both graduate and undergraduate credit work in any field of study on all 10 campuses of the University of Hawai'i System. "
    }, 
    {
      "title": "Manoa Opportunity Grant",
      "date": "2020-Present",
      "awarder": "University of Hawaii at Manoa",
      "summary": "Mānoa Opportunity Grant is available to students who demonstrate financial need based on information provided on your FAFSA. Due to limited funding, the maximum annual UHM award is $4,000 and is dependent upon tuition charged and enrollment status. For undergraduates, this grant is for first time Bachelor's degree seekers. You must be enrolled at least half-time in UH Mānoa courses (6 credits as an undergraduate or 4 credits as a graduate student) to receive the Mānoa Opportunity Grant. Graduate students enrolled in a 1 credit full-time course will not be considered for this grant. The grant will be prorated based upon your enrollment in UH Mānoa courses when not at full time."
    }, 
    {
      "title": "Nā Hoʻokama ",
      "date": "2020-Present",
      "awarder": "Kamehameha Schools",
      "summary": "A scholarship to nurture the dreams of Native Hawaiian learners to grow as ‘ōiwi leaders. NHAP is available to undergraduate and graduate students who demonstrate financial need. There are no additional eligibility requirements to be considered eligible for application review."
    }
  ],
  "references": [
    {
      "name": "Available upon request",
      "reference": ""
    }
  ]
}
